MANIFEST.in
README.rst
setup.cfg
setup.py
requirements/dev.txt
requirements/docs.txt
requirements/tests.txt
slice_aggregator/__about__.py
slice_aggregator/__init__.py
slice_aggregator/by_ixs.py
slice_aggregator/by_slices.py
slice_aggregator/heap.py
slice_aggregator.egg-info/PKG-INFO
slice_aggregator.egg-info/SOURCES.txt
slice_aggregator.egg-info/dependency_links.txt
slice_aggregator.egg-info/top_level.txt