Metadata-Version: 1.2
Name: slice-aggregator
Version: 0.1.1
Summary: A library for aggregating values assigned to indices by slices and the other way around 
Home-page: https://github.com/bm371613/slice-aggregator
Author: Bartosz Marcinkowski
Author-email: bm371613@gmail.com
License: MIT
Project-URL: Documentation, https://slice-aggregator.readthedocs.io/
Project-URL: Source, https://github.com/bm371613/slice-aggregator/
Project-URL: Tracker, https://github.com/bm371613/slice-aggregator/issues
Platform: UNKNOWN
Classifier: Development Status :: 3 - Alpha
Classifier: License :: OSI Approved :: MIT License
Classifier: Programming Language :: Python :: 3
Classifier: Programming Language :: Python :: 3.5
Classifier: Programming Language :: Python :: 3.6
Requires-Python: >=3.5
